fastapi_state/__init__.py
fastapi_state/py.typed
fastapi_state-0.1.0.dist-info/licenses/LICENSE
fastapi_state-0.1.0.dist-info/WHEEL
fastapi_state-0.1.0.dist-info/METADATA
fastapi_state-0.1.0.dist-info/RECORD
