Metadata-Version: 2.4
Name: fastapi-state
Version: 0.1.0
Summary: Simple state management utilities for FastAPI applications.
Author: Petr Tsymbarovich
Author-email: Petr Tsymbarovich <petr@tsymbarovich.ru>
License-File: LICENSE
Classifier: Development Status :: 4 - Beta
Classifier: Framework :: FastAPI
Classifier: Intended Audience :: Developers
Classifier: License :: OSI Approved :: MIT License
Classifier: Programming Language :: Python
Classifier: Typing :: Typed
Requires-Dist: fastapi>=0.115,<1.0
Requires-Python: >=3.12
Project-URL: Homepage, https://github.com/AgroDT/fastapi-state
Project-URL: Issues, https://github.com/AgroDT/fastapi-state/issues
Project-URL: Repository, https://github.com/AgroDT/fastapi-state
